ihu/__init__.py
ihu/_nbdev.py
ihu/core.py
ihu/herm.py
ihu/reshape.py
ihu/tests.py
ihu/unitary.py
ihu-0.0.1.dist-info/LICENSE
ihu-0.0.1.dist-info/METADATA
ihu-0.0.1.dist-info/WHEEL
ihu-0.0.1.dist-info/entry_points.txt
ihu-0.0.1.dist-info/top_level.txt
ihu-0.0.1.dist-info/RECORD
